<?xml version="1.0" encoding="utf-8"?>
<odoo>
    <data>
        <template id="assets_frontend" inherit_id="website.assets_frontend">
            <xpath expr="." position="inside">
                <link rel="stylesheet" type="text/css" href="/stem_frontend_theme/static/src/css/datatables.min.css"/>
                
            	<link rel="stylesheet" 
                    type="text/css"
                    href="/stem_frontend_theme/static/src/css/font-face.css"/>
                <link rel="stylesheet" 
                    type="text/css"
                    href="/stem_frontend_theme/static/src/css/style.css"/>
                <link rel="stylesheet" 
                    type="text/css"
                    href="/stem_frontend_theme/static/src/fonts/font.css"/>
                <link rel="stylesheet" 
                    type="text/css"
                    href="/stem_frontend_theme/static/src/css/datepicker.css"/>
                <link rel="stylesheet" 
                    type="text/css"
                    href="/stem_frontend_theme/static/src/css/main.css"/>
                <link rel="stylesheet" 
                    type="text/css"
                    href="/stem_frontend_theme/static/src/css/typeahead.css"/>
                
                <script type="text/javascript" src="/stem_frontend_theme/static/src/js/datatables.min.js"></script>
                <script type="text/javascript" src="/stem_frontend_theme/static/src/js/typeahead.bundle.js"></script>
                <script type="text/javascript" src="/stem_frontend_theme/static/src/js/datepicker.js"></script>
                <script type="text/javascript" src="/stem_frontend_theme/static/src/js/parent.js"></script>
                <script type="text/javascript" src="/stem_frontend_theme/static/src/js/menu.js"></script>
                <script type="text/javascript" src="/stem_frontend_theme/static/src/js/main.js"></script>
            </xpath>
        </template>
    </data>
</odoo>
